Metadata-Version: 2.4
Name: llama-index-readers-jaguar
Version: 0.4.0
Summary: llama-index readers jaguar integration
Author-email: Your Name <you@example.com>
License-Expression: MIT
License-File: LICENSE
Requires-Python: <4.0,>=3.9
Requires-Dist: jaguardb-http-client<4,>=3.4.2
Requires-Dist: llama-index-core<0.14,>=0.13.0
